trakt_downloader/TraktPuller.py
trakt_downloader/__init__.py
trakt_downloader/configuration.py
trakt_downloader/deluge_connection.py
trakt_downloader/popcorn_interface.py
trakt_downloader/torrent_db.py
trakt_downloader/trakt_connection.py
trakt_downloader/trakt_credentials.py
trakt_downloader/trakt_pull.py
trakt_downloader-0.7.dist-info/METADATA
trakt_downloader-0.7.dist-info/WHEEL
trakt_downloader-0.7.dist-info/entry_points.txt
trakt_downloader-0.7.dist-info/top_level.txt
trakt_downloader-0.7.dist-info/RECORD
