Metadata-Version: 2.1
Name: trakt-downloader
Version: 0.7
Summary: Ever remember a film and want to watch it right away? Well that used to be difficult. Until now.
Home-page: https://github.com/TheSelectiveOppidan/trakt-downloader
Author: The Selective Oppidan
Author-email: theselectiveoppidan@gmail.com
License: MIT
Platform: UNKNOWN
Requires-Python: >=3.6
Requires-Dist: sqlalchemy
Requires-Dist: deluge-client
